modular/__init__.py
modular/dataloader.py
modular/engine.py
modular/utils/__init__.py
modular/utils/default_args.py
modular/utils/functional.py
modular/utils/plots.py
modular/utils/types.py
pyburn_modular-0.1.1.dist-info/METADATA
pyburn_modular-0.1.1.dist-info/WHEEL
pyburn_modular-0.1.1.dist-info/RECORD
