Metadata-Version: 2.1
Name: pyburn-modular
Version: 0.1.1
Summary: The built-in functions often used during training with PyTorch
Author: philn
Requires-Python: >=3.10,<4.0
Classifier: Programming Language :: Python :: 3
Classifier: Programming Language :: Python :: 3.10
Classifier: Programming Language :: Python :: 3.11
Classifier: Programming Language :: Python :: 3.12
Requires-Dist: matplotlib (>=3.9.2,<4.0.0)
Requires-Dist: numpy (>=2.1.0,<3.0.0)
Requires-Dist: pillow (>=10.4.0,<11.0.0)
Requires-Dist: scikit-learn (>=1.5.1,<2.0.0)
Requires-Dist: seaborn (>=0.13.2,<0.14.0)
Requires-Dist: torch (>=2.4.0,<3.0.0)
Requires-Dist: torchvision (>=0.19.0,<0.20.0)
